freertos_visualizer/__init__.py
freertos_visualizer/visualize.py
freertos_visualizer-0.1.4.dist-info/LICENSE
freertos_visualizer-0.1.4.dist-info/METADATA
freertos_visualizer-0.1.4.dist-info/WHEEL
freertos_visualizer-0.1.4.dist-info/entry_points.txt
freertos_visualizer-0.1.4.dist-info/RECORD
