Metadata-Version: 2.1
Name: freertos-visualizer
Version: 0.1.4
Summary: A Python tool for real-time FreeRTOS task state visualization
Home-page: https://github.com/hariharanragothaman/freeRTOS-visualizer
License: MIT
Keywords: FreeRTOS,visualizer,real-time,Python
Author: Hariharan Ragothaman
Author-email: hariharanragothaman@gmail.com
Requires-Python: >=3.9,<4.0
Classifier: License :: OSI Approved :: MIT License
Classifier: Operating System :: OS Independent
Classifier: Programming Language :: Python :: 3
Classifier: Programming Language :: Python :: 3.9
Classifier: Programming Language :: Python :: 3.10
Classifier: Programming Language :: Python :: 3.11
Classifier: Programming Language :: Python :: 3.12
Requires-Dist: PyQt5 (>=5.15,<6.0)
Requires-Dist: matplotlib (>=3.4,<4.0)
Requires-Dist: pyserial (>=3.5,<4.0)
Project-URL: Repository, https://github.com/hariharanragothaman/freeRTOS-visualizer
